setup.cfg
setup.py
mlp/__init__.py
mlp/model.py
mlp/utils.py
mlp.egg-info/PKG-INFO
mlp.egg-info/SOURCES.txt
mlp.egg-info/dependency_links.txt
mlp.egg-info/requires.txt
mlp.egg-info/top_level.txt