Metadata-Version: 1.1
Name: mlp
Version: 0.4.8
Summary: A multilayer perceptron implementation using keras and compatible with scikit-learn
Home-page: https://github.com/alvarouc/mlp
Author: Alvaro Ulloa
Author-email: alvarouc@gmail.com
License: UNKNOWN
Download-URL: https://github.com/alvarouc/mlp/tarball/0.4.8
Keywords: neural net,mlp,deep learning
Platform: UNKNOWN
